Metadata-Version: 2.1
Name: deepspeech-server
Version: 3.0.1
Summary: server for mozilla deepspeech
Home-page: https://github.com/MainRo/deepspeech-server.git
Author: Romain Picard
Author-email: romain.picard@oakbits.com
License: MPL-2.0
Platform: any
Classifier: Development Status :: 3 - Alpha
Classifier: License :: OSI Approved :: Mozilla Public License 2.0 (MPL 2.0)
Classifier: Intended Audience :: Developers
Classifier: Programming Language :: Python :: 3
Classifier: Topic :: Scientific/Engineering :: Artificial Intelligence
License-File: LICENSE
